[{"model": "auth.permission", "pk": 1, "fields": {"name": "Can add log entry", "content_type": 1, "codename": "add_logentry"}}, {"model": "auth.permission", "pk": 2, "fields": {"name": "Can change log entry", "content_type": 1, "codename": "change_logentry"}}, {"model": "auth.permission", "pk": 3, "fields": {"name": "Can delete log entry", "content_type": 1, "codename": "delete_logentry"}}, {"model": "auth.permission", "pk": 4, "fields": {"name": "Can view log entry", "content_type": 1, "codename": "view_logentry"}}, {"model": "auth.permission", "pk": 5, "fields": {"name": "Can add permission", "content_type": 2, "codename": "add_permission"}}, {"model": "auth.permission", "pk": 6, "fields": {"name": "Can change permission", "content_type": 2, "codename": "change_permission"}}, {"model": "auth.permission", "pk": 7, "fields": {"name": "Can delete permission", "content_type": 2, "codename": "delete_permission"}}, {"model": "auth.permission", "pk": 8, "fields": {"name": "Can view permission", "content_type": 2, "codename": "view_permission"}}, {"model": "auth.permission", "pk": 9, "fields": {"name": "Can add group", "content_type": 3, "codename": "add_group"}}, {"model": "auth.permission", "pk": 10, "fields": {"name": "Can change group", "content_type": 3, "codename": "change_group"}}, {"model": "auth.permission", "pk": 11, "fields": {"name": "Can delete group", "content_type": 3, "codename": "delete_group"}}, {"model": "auth.permission", "pk": 12, "fields": {"name": "Can view group", "content_type": 3, "codename": "view_group"}}, {"model": "auth.permission", "pk": 13, "fields": {"name": "Can add content type", "content_type": 4, "codename": "add_contenttype"}}, {"model": "auth.permission", "pk": 14, "fields": {"name": "Can change content type", "content_type": 4, "codename": "change_contenttype"}}, {"model": "auth.permission", "pk": 15, "fields": {"name": "Can delete content type", "content_type": 4, "codename": "delete_contenttype"}}, {"model": "auth.permission", "pk": 16, "fields": {"name": "Can view content type", "content_type": 4, "codename": "view_contenttype"}}, {"model": "auth.permission", "pk": 17, "fields": {"name": "Can add session", "content_type": 5, "codename": "add_session"}}, {"model": "auth.permission", "pk": 18, "fields": {"name": "Can change session", "content_type": 5, "codename": "change_session"}}, {"model": "auth.permission", "pk": 19, "fields": {"name": "Can delete session", "content_type": 5, "codename": "delete_session"}}, {"model": "auth.permission", "pk": 20, "fields": {"name": "Can view session", "content_type": 5, "codename": "view_session"}}, {"model": "auth.permission", "pk": 21, "fields": {"name": "Can add users groups", "content_type": 6, "codename": "add_usersgroups"}}, {"model": "auth.permission", "pk": 22, "fields": {"name": "Can change users groups", "content_type": 6, "codename": "change_usersgroups"}}, {"model": "auth.permission", "pk": 23, "fields": {"name": "Can delete users groups", "content_type": 6, "codename": "delete_usersgroups"}}, {"model": "auth.permission", "pk": 24, "fields": {"name": "Can view users groups", "content_type": 6, "codename": "view_usersgroups"}}, {"model": "auth.permission", "pk": 25, "fields": {"name": "Can add users types", "content_type": 7, "codename": "add_userstypes"}}, {"model": "auth.permission", "pk": 26, "fields": {"name": "Can change users types", "content_type": 7, "codename": "change_userstypes"}}, {"model": "auth.permission", "pk": 27, "fields": {"name": "Can delete users types", "content_type": 7, "codename": "delete_userstypes"}}, {"model": "auth.permission", "pk": 28, "fields": {"name": "Can view users types", "content_type": 7, "codename": "view_userstypes"}}, {"model": "auth.permission", "pk": 29, "fields": {"name": "Can add user", "content_type": 8, "codename": "add_users"}}, {"model": "auth.permission", "pk": 30, "fields": {"name": "Can change user", "content_type": 8, "codename": "change_users"}}, {"model": "auth.permission", "pk": 31, "fields": {"name": "Can delete user", "content_type": 8, "codename": "delete_users"}}, {"model": "auth.permission", "pk": 32, "fields": {"name": "Can view user", "content_type": 8, "codename": "view_users"}}, {"model": "auth.permission", "pk": 33, "fields": {"name": "Can add events", "content_type": 9, "codename": "add_events"}}, {"model": "auth.permission", "pk": 34, "fields": {"name": "Can change events", "content_type": 9, "codename": "change_events"}}, {"model": "auth.permission", "pk": 35, "fields": {"name": "Can delete events", "content_type": 9, "codename": "delete_events"}}, {"model": "auth.permission", "pk": 36, "fields": {"name": "Can view events", "content_type": 9, "codename": "view_events"}}, {"model": "auth.permission", "pk": 37, "fields": {"name": "Can add places", "content_type": 10, "codename": "add_places"}}, {"model": "auth.permission", "pk": 38, "fields": {"name": "Can change places", "content_type": 10, "codename": "change_places"}}, {"model": "auth.permission", "pk": 39, "fields": {"name": "Can delete places", "content_type": 10, "codename": "delete_places"}}, {"model": "auth.permission", "pk": 40, "fields": {"name": "Can view places", "content_type": 10, "codename": "view_places"}}, {"model": "auth.permission", "pk": 41, "fields": {"name": "Can add tickets", "content_type": 11, "codename": "add_tickets"}}, {"model": "auth.permission", "pk": 42, "fields": {"name": "Can change tickets", "content_type": 11, "codename": "change_tickets"}}, {"model": "auth.permission", "pk": 43, "fields": {"name": "Can delete tickets", "content_type": 11, "codename": "delete_tickets"}}, {"model": "auth.permission", "pk": 44, "fields": {"name": "Can view tickets", "content_type": 11, "codename": "view_tickets"}}, {"model": "auth.permission", "pk": 45, "fields": {"name": "Can add requirements", "content_type": 12, "codename": "add_requirements"}}, {"model": "auth.permission", "pk": 46, "fields": {"name": "Can change requirements", "content_type": 12, "codename": "change_requirements"}}, {"model": "auth.permission", "pk": 47, "fields": {"name": "Can delete requirements", "content_type": 12, "codename": "delete_requirements"}}, {"model": "auth.permission", "pk": 48, "fields": {"name": "Can view requirements", "content_type": 12, "codename": "view_requirements"}}, {"model": "contenttypes.contenttype", "id": 1, "fields": {"app_label": "admin", "model": "logentry"}}, {"model": "contenttypes.contenttype", "id": 2, "fields": {"app_label": "auth", "model": "permission"}}, {"model": "contenttypes.contenttype", "id": 3, "fields": {"app_label": "auth", "model": "group"}}, {"model": "contenttypes.contenttype", "id": 4, "fields": {"app_label": "contenttypes", "model": "contenttype"}}, {"model": "contenttypes.contenttype", "id": 5, "fields": {"app_label": "sessions", "model": "session"}}, {"model": "contenttypes.contenttype", "id": 6, "fields": {"app_label": "users", "model": "usersgroups"}}, {"model": "contenttypes.contenttype", "id": 7, "fields": {"app_label": "users", "model": "userstypes"}}, {"model": "contenttypes.contenttype", "id": 8, "fields": {"app_label": "users", "model": "users"}}, {"model": "contenttypes.contenttype", "id": 9, "fields": {"app_label": "events", "model": "events"}}, {"model": "contenttypes.contenttype", "id": 10, "fields": {"app_label": "events", "model": "places"}}, {"model": "contenttypes.contenttype", "id": 11, "fields": {"app_label": "events", "model": "tickets"}}, {"model": "contenttypes.contenttype", "id": 12, "fields": {"app_label": "requirements", "model": "requirements"}}, {"model": "users.users", "pk": 1, "fields": {"password": "pbkdf2_sha256$216000$4acsfBLCbxAk$4nwbvWRBANFFEb3t7o4XDRQTTOTJig82TFjV7juu27g=", "is_superuser": false, "is_staff": false, "is_active": true, "first_name": "Neddie", "last_name": "Barthelet", "email": "nbarthelet0@examiner.com", "title": null, "user_permissions": [], "groups": [], "types": []}}, {"model": "users.users", "pk": 2, "fields": {"password": "pbkdf2_sha256$216000$EV7d2vhIg0CX$TydEcM4cV4OD/Lm/Q3lD0f++lm6N23cMFi+L9spUwO8=", "is_superuser": false, "is_staff": false, "is_active": true, "first_name": "Bibby", "last_name": "Caulder", "email": "bcaulder1@amazon.co.uk", "title": null, "user_permissions": [], "groups": [], "types": []}}, {"model": "users.users", "pk": 3, "fields": {"password": "pbkdf2_sha256$216000$gCjcuIN5sXUj$05D3D6HW8Sy6kIjD0aKwhy4HkuICzhikry5zHpZ8R/8=", "is_superuser": false, "is_staff": false, "is_active": true, "first_name": "Michale", "last_name": "Allcroft", "email": "mallcroft2@stumbleupon.com", "title": null, "user_permissions": [], "groups": [], "types": []}}, {"model": "users.users", "pk": 4, "fields": {"password": "pbkdf2_sha256$216000$8xf9dySPoICf$AZQ9uF6bCuSzGZ1Cf06Bcld7gz7HPdHduDqJe59XbLo=", "is_superuser": false, "is_staff": false, "is_active": true, "first_name": "Elden", "last_name": "Worge", "email": "eworge3@techcrunch.com", "title": null, "user_permissions": [], "groups": [], "types": []}}, {"model": "users.users", "pk": 5, "fields": {"password": "pbkdf2_sha256$216000$CfUTrbDe8bV4$xW7jhI8+g/TnapUCWZ/dsEGxqFwelzPL/dPlx7wT9Qw=", "is_superuser": false, "is_staff": false, "is_active": true, "first_name": "Vance", "last_name": "Aimable", "email": "vaimable4@163.com", "title": null, "user_permissions": [], "groups": [], "types": []}}, {"model": "users.users", "pk": 6, "fields": {"password": "pbkdf2_sha256$216000$Zj4zqM7zoiyR$Pn/eK3/dGGxzfVMZB2EtQ5l9INoCHl1DfmhNtgmu3ts=", "is_superuser": false, "is_staff": false, "is_active": true, "first_name": "Miranda", "last_name": "Medwell", "email": "mmedwell5@flavors.me", "title": null, "user_permissions": [], "groups": [], "types": []}}, {"model": "users.users", "pk": 7, "fields": {"password": "pbkdf2_sha256$216000$Pj3Fs1WyXUPs$Wds8tNyBMVehn/ar/MkgYiGa2BDqefUfeKg+Cfr+v9I=", "is_superuser": false, "is_staff": false, "is_active": true, "first_name": "Thor", "last_name": "Bassindale", "email": "tbassindale6@businessinsider.com", "title": null, "user_permissions": [], "groups": [], "types": []}}, {"model": "users.users", "pk": 8, "fields": {"password": "pbkdf2_sha256$216000$l5X7dC5uiw5v$1DYHXlRQgYFEBp3iaIxFE7s4PJUDQNLGJY4y9crfDoE=", "is_superuser": false, "is_staff": false, "is_active": true, "first_name": "Fransisco", "last_name": "Brickner", "email": "fbrickner7@ebay.co.uk", "title": null, "user_permissions": [], "groups": [], "types": []}}, {"model": "users.users", "pk": 9, "fields": {"password": "pbkdf2_sha256$216000$lf7VK1lVl2Kh$14wBpCqcyLEAgCW6/yE+AHCB1PW+sxmJqtTGvWlqMjY=", "is_superuser": false, "is_staff": false, "is_active": true, "first_name": "Lenore", "last_name": "Navarro", "email": "lnavarro8@auda.org.au", "title": null, "user_permissions": [], "groups": [], "types": []}}, {"model": "users.users", "pk": 10, "fields": {"password": "pbkdf2_sha256$216000$xtEi2HUnaHYJ$pZTny9bnpwBa0zalOgBdNFpGBj90DSjaAOWwEIHYTJk=", "is_superuser": false, "is_staff": false, "is_active": true, "first_name": "Tonie", "last_name": "Cordell", "email": "tcordell9@fastcompany.com", "title": null, "user_permissions": [], "groups": [], "types": []}}, {"model": "events.places", "pk": 1, "fields": {"name": "Sierra 1500", "address": "833 Straubel Trail"}}, {"model": "events.places", "pk": 2, "fields": {"name": "Impreza", "address": "86222 Nancy Pass"}}, {"model": "events.places", "pk": 3, "fields": {"name": "Pajero", "address": "3 Oneill Way"}}, {"model": "events.places", "pk": 4, "fields": {"name": "Century", "address": "277 Anthes Center"}}, {"model": "events.places", "pk": 5, "fields": {"name": "Silverado", "address": "54855 Everett Alley"}}, {"model": "events.places", "pk": 6, "fields": {"name": "Mustang", "address": "9131 Twin Pines Drive"}}, {"model": "events.places", "pk": 7, "fields": {"name": "Neon", "address": "6262 Hovde Park"}}, {"model": "events.places", "pk": 8, "fields": {"name": "Avalanche 1500", "address": "918 Rutledge Trail"}}, {"model": "events.places", "pk": 9, "fields": {"name": "SL-Class", "address": "4145 Fremont Parkway"}}, {"model": "events.places", "pk": 10, "fields": {"name": "LHS", "address": "466 Little Fleur Place"}}, {"model": "events.events", "pk": 1, "fields": {"name": "Neophoca cinerea", "start": "2020-11-26T00:40:13Z", "end": "2020-12-27T11:26:25Z", "limit_of_participants": 50, "number_of_participants": 0, "price": "91.18", "place": 1, "requirements": 1, "lecturers": [8], "participants": []}}, {"model": "events.events", "pk": 2, "fields": {"name": "Mazama gouazoubira", "start": "2019-12-18T21:49:24Z", "end": "2021-04-01T19:25:54Z", "limit_of_participants": 83, "number_of_participants": 0, "price": "28.02", "place": 4, "requirements": 2, "lecturers": [3, 10], "participants": []}}, {"model": "events.events", "pk": 3, "fields": {"name": "Theropithecus gelada", "start": "2020-12-08T14:53:06Z", "end": "2021-02-21T02:52:15Z", "limit_of_participants": 38, "number_of_participants": 0, "price": "14.27", "place": 3, "requirements": 3, "lecturers": [2], "participants": []}}, {"model": "events.events", "pk": 4, "fields": {"name": "Helogale undulata", "start": "2020-07-13T04:50:49Z", "end": "2021-05-08T02:31:28Z", "limit_of_participants": 67, "number_of_participants": 0, "price": null, "place": 9, "requirements": 4, "lecturers": [9], "participants": []}}, {"model": "events.events", "pk": 5, "fields": {"name": "Melophus lathami", "start": "2020-05-15T05:30:49Z", "end": "2021-04-18T18:46:31Z", "limit_of_participants": 94, "number_of_participants": 0, "price": "93.13", "place": 4, "requirements": 5, "lecturers": [3, 5], "participants": []}}, {"model": "events.events", "pk": 6, "fields": {"name": "Dasypus novemcinctus", "start": "2020-10-31T16:36:25Z", "end": "2021-03-15T12:51:41Z", "limit_of_participants": 38, "number_of_participants": 0, "price": "94.64", "place": 9, "requirements": 6, "lecturers": [9], "participants": []}}, {"model": "events.events", "pk": 7, "fields": {"name": "Ovis ammon", "start": "2020-04-22T07:26:12Z", "end": "2021-01-12T15:23:38Z", "limit_of_participants": 61, "number_of_participants": 0, "price": "55.86", "place": 5, "requirements": 7, "lecturers": [9, 10], "participants": []}}, {"model": "events.events", "pk": 8, "fields": {"name": "Pseudalopex gymnocercus", "start": "2020-08-09T09:39:36Z", "end": "2020-12-26T23:37:42Z", "limit_of_participants": 36, "number_of_participants": 0, "price": "60.48", "place": 3, "requirements": 8, "lecturers": [6], "participants": []}}, {"model": "events.events", "pk": 9, "fields": {"name": "Columba livia", "start": "2020-01-18T17:54:11Z", "end": "2021-02-14T11:24:46Z", "limit_of_participants": 87, "number_of_participants": 0, "price": "80.52", "place": 8, "requirements": 9, "lecturers": [8], "participants": []}}, {"model": "events.events", "pk": 10, "fields": {"name": "Ara ararauna", "start": "2020-07-16T16:02:47Z", "end": "2021-01-13T11:47:11Z", "limit_of_participants": 85, "number_of_participants": 0, "price": "44.33", "place": 6, "requirements": 10, "lecturers": [1], "participants": []}}, {"model": "events.events", "pk": 11, "fields": {"name": "Papio cynocephalus", "start": "2020-01-06T10:09:13Z", "end": "2021-05-24T07:57:29Z", "limit_of_participants": 60, "number_of_participants": 0, "price": "13.97", "place": 6, "requirements": 11, "lecturers": [5, 9], "participants": []}}, {"model": "events.events", "pk": 12, "fields": {"name": "Haliaeetus leucocephalus", "start": "2020-07-02T10:36:54Z", "end": "2021-02-10T03:43:53Z", "limit_of_participants": 8, "number_of_participants": 0, "price": "71.88", "place": 6, "requirements": 12, "lecturers": [3], "participants": []}}, {"model": "events.events", "pk": 13, "fields": {"name": "unavailable", "start": "2020-11-19T15:26:03Z", "end": "2021-05-26T07:00:34Z", "limit_of_participants": 51, "number_of_participants": 0, "price": "39.20", "place": 8, "requirements": 13, "lecturers": [3, 5], "participants": []}}, {"model": "events.events", "pk": 14, "fields": {"name": "Marmota flaviventris", "start": "2020-08-26T19:45:47Z", "end": "2021-01-07T19:50:00Z", "limit_of_participants": 34, "number_of_participants": 0, "price": "74.88", "place": 7, "requirements": 14, "lecturers": [10], "participants": []}}, {"model": "events.events", "pk": 15, "fields": {"name": "Mustela nigripes", "start": "2020-02-21T03:24:01Z", "end": "2021-04-23T20:06:13Z", "limit_of_participants": 28, "number_of_participants": 0, "price": "95.27", "place": 6, "requirements": 15, "lecturers": [6], "participants": []}}, {"model": "events.events", "pk": 16, "fields": {"name": "Ara macao", "start": "2020-08-07T19:07:59Z", "end": "2021-05-20T21:18:41Z", "limit_of_participants": 71, "number_of_participants": 0, "price": "36.57", "place": 4, "requirements": 16, "lecturers": [3], "participants": []}}, {"model": "events.events", "pk": 17, "fields": {"name": "Rhabdomys pumilio", "start": "2020-10-29T07:00:25Z", "end": "2021-04-20T19:29:21Z", "limit_of_participants": 47, "number_of_participants": 0, "price": null, "place": 6, "requirements": 17, "lecturers": [5, 8], "participants": []}}, {"model": "events.events", "pk": 18, "fields": {"name": "Pycnonotus barbatus", "start": "2020-02-14T22:32:54Z", "end": "2021-03-01T07:40:30Z", "limit_of_participants": 30, "number_of_participants": 0, "price": "84.85", "place": 2, "requirements": 18, "lecturers": [4, 6], "participants": []}}, {"model": "events.events", "pk": 19, "fields": {"name": "Melursus ursinus", "start": "2020-01-29T14:59:52Z", "end": "2021-02-21T07:50:47Z", "limit_of_participants": 64, "number_of_participants": 0, "price": null, "place": 2, "requirements": 19, "lecturers": [2], "participants": []}}, {"model": "events.events", "pk": 20, "fields": {"name": "Columba palumbus", "start": "2020-01-12T13:28:33Z", "end": "2021-05-01T04:47:06Z", "limit_of_participants": 22, "number_of_participants": 0, "price": "89.49", "place": 6, "requirements": 20, "lecturers": [1, 6], "participants": []}}, {"model": "events.events", "pk": 21, "fields": {"name": "Canis mesomelas", "start": "2020-08-05T06:12:10Z", "end": "2021-01-22T16:04:47Z", "limit_of_participants": 32, "number_of_participants": 0, "price": "32.80", "place": 3, "requirements": 21, "lecturers": [4], "participants": []}}, {"model": "events.events", "pk": 22, "fields": {"name": "Cygnus atratus", "start": "2020-04-01T20:10:33Z", "end": "2021-01-26T01:43:03Z", "limit_of_participants": 89, "number_of_participants": 0, "price": "58.46", "place": 5, "requirements": 22, "lecturers": [7], "participants": []}}, {"model": "events.events", "pk": 23, "fields": {"name": "Ardea cinerea", "start": "2020-01-11T08:21:24Z", "end": "2021-03-22T16:16:26Z", "limit_of_participants": 30, "number_of_participants": 0, "price": "27.53", "place": 6, "requirements": 23, "lecturers": [5, 9], "participants": []}}, {"model": "events.events", "pk": 24, "fields": {"name": "Connochaetus taurinus", "start": "2020-08-17T05:17:56Z", "end": "2021-02-24T20:05:45Z", "limit_of_participants": 13, "number_of_participants": 0, "price": "82.40", "place": 8, "requirements": 24, "lecturers": [3, 8], "participants": []}}, {"model": "events.events", "pk": 25, "fields": {"name": "Tringa glareola", "start": "2020-07-15T22:38:46Z", "end": "2020-12-22T15:29:06Z", "limit_of_participants": 87, "number_of_participants": 0, "price": null, "place": 8, "requirements": 25, "lecturers": [2, 4], "participants": []}}, {"model": "events.events", "pk": 26, "fields": {"name": "Equus burchelli", "start": "2020-06-28T20:46:23Z", "end": "2021-03-14T19:52:12Z", "limit_of_participants": 39, "number_of_participants": 0, "price": null, "place": 7, "requirements": 26, "lecturers": [9], "participants": []}}, {"model": "events.events", "pk": 27, "fields": {"name": "Taxidea taxus", "start": "2020-08-09T11:19:20Z", "end": "2021-04-22T18:58:55Z", "limit_of_participants": 11, "number_of_participants": 0, "price": "63.14", "place": 10, "requirements": 27, "lecturers": [2, 9], "participants": []}}, {"model": "events.events", "pk": 28, "fields": {"name": "Bison bison", "start": "2020-03-09T21:43:23Z", "end": "2021-01-10T09:00:53Z", "limit_of_participants": 34, "number_of_participants": 0, "price": null, "place": 5, "requirements": 28, "lecturers": [10], "participants": []}}, {"model": "events.events", "pk": 29, "fields": {"name": "Mazama gouazoubira", "start": "2020-11-17T05:15:38Z", "end": "2021-02-07T03:57:32Z", "limit_of_participants": 92, "number_of_participants": 0, "price": "81.51", "place": 4, "requirements": 29, "lecturers": [3], "participants": []}}, {"model": "events.events", "pk": 30, "fields": {"name": "Ara chloroptera", "start": "2020-06-05T16:48:47Z", "end": "2021-04-23T12:41:13Z", "limit_of_participants": 1, "number_of_participants": 0, "price": null, "place": 9, "requirements": 30, "lecturers": [3, 6], "participants": []}}, {"model": "requirements.requirements", "pk": 1, "fields": {"requirement_json": "[{\"type\": \"DOES_NOT_BELONG_TO_ANY_OF\", \"groups\": [\"Students\", \"Lecturers\", \"APSI\"]}, {\"type\": \"BELONGS_TO_ANY_OF\", \"groups\": [\"APSI\", \"Guests\"]}]"}}, {"model": "requirements.requirements", "pk": 2, "fields": {"requirement_json": "[{\"type\": \"BELONGS_EXACTLY_TO\", \"groups\": [\"Students\", \"Lecturers\"]}, {\"type\": \"BELONGS_EXACTLY_TO\", \"groups\": [\"Guests\"]}]"}}, {"model": "requirements.requirements", "pk": 3, "fields": {"requirement_json": "[{\"type\": \"BELONGS_TO_ANY_OF\", \"groups\": [\"Lecturers\", \"APSI\", \"Guests\"]}, {\"type\": \"BELONGS_EXACTLY_TO\", \"groups\": [\"Guests\"]}]"}}, {"model": "requirements.requirements", "pk": 4, "fields": {"requirement_json": "[]"}}, {"model": "requirements.requirements", "pk": 5, "fields": {"requirement_json": "[{\"type\": \"BELONGS_TO_ANY_OF\", \"groups\": [\"Guests\"]}]"}}, {"model": "requirements.requirements", "pk": 6, "fields": {"requirement_json": "[{\"type\": \"BELONGS_TO_ANY_OF\", \"groups\": [\"APSI\"]}, {\"type\": \"BELONGS_EXACTLY_TO\", \"groups\": [\"Guests\"]}]"}}, {"model": "requirements.requirements", "pk": 7, "fields": {"requirement_json": "[{\"type\": \"BELONGS_EXACTLY_TO\", \"groups\": [\"Guests\"]}, {\"type\": \"BELONGS_TO_ANY_OF\", \"groups\": [\"APSI\"]}]"}}, {"model": "requirements.requirements", "pk": 8, "fields": {"requirement_json": "[{\"type\": \"BELONGS_TO_ANY_OF\", \"groups\": [\"APSI\", \"Guests\"]}]"}}, {"model": "requirements.requirements", "pk": 9, "fields": {"requirement_json": "[{\"type\": \"BELONGS_EXACTLY_TO\", \"groups\": [\"Lecturers\", \"Students\"]}, {\"type\": \"DOES_NOT_BELONG_TO_ANY_OF\", \"groups\": [\"APSI\", \"Guests\"]}]"}}, {"model": "requirements.requirements", "pk": 10, "fields": {"requirement_json": "[{\"type\": \"BELONGS_TO_ANY_OF\", \"groups\": [\"Students\", \"Guests\"]}, {\"type\": \"BELONGS_TO_ANY_OF\", \"groups\": [\"APSI\", \"Lecturers\", \"Guests\"]}]"}}, {"model": "requirements.requirements", "pk": 11, "fields": {"requirement_json": "[{\"type\": \"BELONGS_EXACTLY_TO\", \"groups\": [\"Guests\", \"Lecturers\", \"Students\"]}, {\"type\": \"BELONGS_EXACTLY_TO\", \"groups\": [\"Guests\"]}]"}}, {"model": "requirements.requirements", "pk": 12, "fields": {"requirement_json": "[{\"type\": \"DOES_NOT_BELONG_TO_ANY_OF\", \"groups\": [\"Lecturers\"]}]"}}, {"model": "requirements.requirements", "pk": 13, "fields": {"requirement_json": "[{\"type\": \"BELONGS_TO_ANY_OF\", \"groups\": [\"Students\", \"Lecturers\", \"APSI\"]}]"}}, {"model": "requirements.requirements", "pk": 14, "fields": {"requirement_json": "[{\"type\": \"BELONGS_EXACTLY_TO\", \"groups\": [\"Lecturers\", \"APSI\"]}, {\"type\": \"BELONGS_TO_ANY_OF\", \"groups\": [\"Students\", \"APSI\", \"Lecturers\"]}]"}}, {"model": "requirements.requirements", "pk": 15, "fields": {"requirement_json": "[{\"type\": \"BELONGS_EXACTLY_TO\", \"groups\": [\"Lecturers\", \"Students\"]}, {\"type\": \"BELONGS_EXACTLY_TO\", \"groups\": [\"APSI\"]}]"}}, {"model": "requirements.requirements", "pk": 16, "fields": {"requirement_json": "[{\"type\": \"BELONGS_TO_ANY_OF\", \"groups\": [\"Students\"]}]"}}, {"model": "requirements.requirements", "pk": 17, "fields": {"requirement_json": "[]"}}, {"model": "requirements.requirements", "pk": 18, "fields": {"requirement_json": "[{\"type\": \"DOES_NOT_BELONG_TO_ANY_OF\", \"groups\": [\"Students\", \"Guests\"]}, {\"type\": \"DOES_NOT_BELONG_TO_ANY_OF\", \"groups\": [\"Students\"]}]"}}, {"model": "requirements.requirements", "pk": 19, "fields": {"requirement_json": "[]"}}, {"model": "requirements.requirements", "pk": 20, "fields": {"requirement_json": "[{\"type\": \"BELONGS_TO_ANY_OF\", \"groups\": [\"Guests\", \"Students\", \"Lecturers\"]}, {\"type\": \"DOES_NOT_BELONG_TO_ANY_OF\", \"groups\": [\"Students\", \"Guests\", \"Lecturers\"]}]"}}, {"model": "requirements.requirements", "pk": 21, "fields": {"requirement_json": "[{\"type\": \"BELONGS_TO_ANY_OF\", \"groups\": [\"Guests\"]}]"}}, {"model": "requirements.requirements", "pk": 22, "fields": {"requirement_json": "[{\"type\": \"DOES_NOT_BELONG_TO_ANY_OF\", \"groups\": [\"Lecturers\", \"APSI\", \"Students\"]}, {\"type\": \"BELONGS_EXACTLY_TO\", \"groups\": [\"Lecturers\", \"Guests\", \"APSI\"]}]"}}, {"model": "requirements.requirements", "pk": 23, "fields": {"requirement_json": "[{\"type\": \"BELONGS_TO_ANY_OF\", \"groups\": [\"Guests\", \"Students\"]}]"}}, {"model": "requirements.requirements", "pk": 24, "fields": {"requirement_json": "[{\"type\": \"BELONGS_TO_ANY_OF\", \"groups\": [\"Lecturers\", \"Students\"]}]"}}, {"model": "requirements.requirements", "pk": 25, "fields": {"requirement_json": "[]"}}, {"model": "requirements.requirements", "pk": 26, "fields": {"requirement_json": "[]"}}, {"model": "requirements.requirements", "pk": 27, "fields": {"requirement_json": "[{\"type\": \"BELONGS_EXACTLY_TO\", \"groups\": [\"APSI\", \"Students\", \"Guests\"]}, {\"type\": \"BELONGS_EXACTLY_TO\", \"groups\": [\"Lecturers\"]}]"}}, {"model": "requirements.requirements", "pk": 28, "fields": {"requirement_json": "[]"}}, {"model": "requirements.requirements", "pk": 29, "fields": {"requirement_json": "[{\"type\": \"BELONGS_TO_ANY_OF\", \"groups\": [\"APSI\", \"Students\", \"Guests\"]}, {\"type\": \"BELONGS_EXACTLY_TO\", \"groups\": [\"Guests\", \"Students\", \"Lecturers\"]}]"}}, {"model": "requirements.requirements", "pk": 30, "fields": {"requirement_json": "[]"}}]
